wtforms_validators/__init__.py
wtforms_validators-1.0.0.dist-info/LICENSE
wtforms_validators-1.0.0.dist-info/METADATA
wtforms_validators-1.0.0.dist-info/WHEEL
wtforms_validators-1.0.0.dist-info/top_level.txt
wtforms_validators-1.0.0.dist-info/RECORD
