Metadata-Version: 2.1
Name: wtforms-validators
Version: 1.0.0
Summary: Validators for wtforms package
Home-page: https://github.com/akhilharihar/wtforms-validators
Author: Akhil Harihar
Author-email: hariharakhil@gmail.com
License: UNKNOWN
Platform: UNKNOWN
Classifier: Programming Language :: Python :: 3
Classifier: License :: OSI Approved :: MIT License
Classifier: Operating System :: OS Independent
Classifier: Environment :: Web Environment
Classifier: Intended Audience :: Developers
Classifier: Development Status :: 5 - Production/Stable
Requires-Python: >=3.0
